ADMCode/__init__.py
ADMCode/ddm.py
ADMCode/visualize.py
AdaptiveDecisionMaking_2018-0.0.1.dist-info/DESCRIPTION.rst
AdaptiveDecisionMaking_2018-0.0.1.dist-info/METADATA
AdaptiveDecisionMaking_2018-0.0.1.dist-info/RECORD
AdaptiveDecisionMaking_2018-0.0.1.dist-info/WHEEL
AdaptiveDecisionMaking_2018-0.0.1.dist-info/metadata.json
AdaptiveDecisionMaking_2018-0.0.1.dist-info/top_level.txt
