Metadata-Version: 2.0
Name: AdaptiveDecisionMaking-2018
Version: 0.0.1
Summary: Code and lab resources for Neural and Cognitive Models of Adaptive Decision Making course (2018)
Home-page: http://github.com/CoAxLab/AdaptiveDecisionMaking_2018
Author: Kyle Dunovan, Timothy Verstynen
Author-email: dunovank@gmail.com
License: UNKNOWN
Platform: UNKNOWN
Classifier: Environment :: Console
Classifier: Operating System :: OS Independent
Classifier: License :: OSI Approved :: MIT License
Classifier: Development Status :: 3 - Alpha
Classifier: Programming Language :: Python
Classifier: Programming Language :: Python :: 3
Classifier: Programming Language :: Python :: 3.4
Classifier: Programming Language :: Python :: 3.6
Classifier: Topic :: Scientific/Engineering
Requires-Dist: numpy
Requires-Dist: scipy
Requires-Dist: pandas
Requires-Dist: matplotlib
Requires-Dist: seaborn
Requires-Dist: scikit-learn
Requires-Dist: numba
Requires-Dist: future
